{"handle":"ae841822-3c1c-438f-a5af-60354c3499c0","p2p_id":"CLLQNMXMZT","pol":14425,"pod":15810,"results":[{"id":"791cb320-0614-11ee-9560-00505683d611","carrier":{"id":116,"short_name":"Hapag-Lloyd","official_name":"Hapag-Lloyd","scac":"HLCU"},"pol":{"id":14425,"name":"Lirquén","locode":"CLLQN","longitude":-72.983333,"latitude":-36.716667},"pod":{"id":15810,"name":"Mazatlan","locode":"MXMZT","longitude":-106.416667,"latitude":23.2},"etd":"2023-06-13T11:00+0000","eta":"2023-07-10T05:00+0000","etd_local":"2023-06-13T07:00-0400","eta_local":"2023-07-09T22:00-0700","legs":[{"pol":{"id":14425,"name":"Lirquén","locode":"CLLQN","longitude":-72.983333,"latitude":-36.716667},"pod":{"id":15770,"name":"Manzanillo","locode":"MXZLO","longitude":-104.333333,"latitude":19.05},"etd":"2023-06-13T11:00+0000","eta":"2023-06-28T14:00+0000","etd_local":"2023-06-13T07:00-0400","eta_local":"2023-06-28T08:00-0600","carrier_id":116,"service_id":5665,"service_name":"SOUTH AMERICA - ASIA - LOOP 2","service_code":"AN2","voyage_number":"FA323R","vessel":{"id":6875,"shipname":"MSC NATASHA XIII","imo":9463035},"quality":0},{"pol":{"id":15770,"name":"Manzanillo","locode":"MXZLO","longitude":-104.333333,"latitude":19.05},"pod":{"id":15810,"name":"Mazatlan","locode":"MXMZT","longitude":-106.416667,"latitude":23.2},"etd":"2023-07-01T15:00+0000","eta":"2023-07-10T05:00+0000","etd_local":"2023-07-01T09:00-0600","eta_local":"2023-07-09T22:00-0700","carrier_id":116,"service_id":5661,"service_name":"CALIFORNIA - CENTRAL AMERICA EXPRESS SERVICE","service_code":"CCE","voyage_number":"0334W","vessel":{"id":83072,"shipname":"FLEUR N","imo":9509138},"quality":0}],"alliance":{"id":999,"name":"Others"},"uuid_p2p":"0723904a-1a3b-4827-b651-ff7e96c59e27","p2p_id":"CLLQNMXMZT","cyclosing":null,"transshipment_count":1,"transit_time":27},{"id":"796844d4-0614-11ee-9560-00505683d611","carrier":{"id":168,"short_name":"ONE","official_name":"Ocean Network Express","scac":"ONEY"},"pol":{"id":14425,"name":"Lirquén","locode":"CLLQN","longitude":-72.983333,"latitude":-36.716667},"pod":{"id":15810,"name":"Mazatlan","locode":"MXMZT","longitude":-106.416667,"latitude":23.2},"etd":"2023-06-27T11:00+0000","eta":"2023-07-23T04:00+0000","etd_local":"2023-06-27T07:00-0400","eta_local":"2023-07-22T21:00-0700","legs":[{"pol":{"id":14425,"name":"Lirquén","locode":"CLLQN","longitude":-72.983333,"latitude":-36.716667},"pod":{"id":15770,"name":"Manzanillo","locode":"MXZLO","longitude":-104.333333,"latitude":19.05},"etd":"2023-06-27T11:00+0000","eta":"2023-07-12T12:00+0000","etd_local":"2023-06-27T07:00-0400","eta_local":"2023-07-12T06:00-0600","carrier_id":168,"service_id":12672,"service_name":"ASIA LATIN AMERICA EXPRESS SERVICE 2 - ALX2","service_code":"AX2","voyage_number":"317W","vessel":{"id":9379754,"shipname":"MSC JOSSELINE","imo":9842061},"quality":0},{"pol":{"id":15770,"name":"Manzanillo","locode":"MXZLO","longitude":-104.333333,"latitude":19.05},"pod":{"id":15810,"name":"Mazatlan","locode":"MXMZT","longitude":-106.416667,"latitude":23.2},"etd":"2023-07-15T15:00+0000","eta":"2023-07-23T04:00+0000","etd_local":"2023-07-15T09:00-0600","eta_local":"2023-07-22T21:00-0700","carrier_id":168,"service_id":12028,"service_name":"MARGARITA NEO - EXPRESS SERVICE - MAREX","service_code":"MAR","voyage_number":"404W","vessel":{"id":23729,"shipname":"NYK SILVIA","imo":9419656},"quality":0}],"alliance":{"id":999,"name":"Others"},"uuid_p2p":"d2d73282-e1a6-4335-9c4a-1a92f898d7d4","p2p_id":"CLLQNMXMZT","cyclosing":null,"transshipment_count":1,"transit_time":26},{"id":"79684092-0614-11ee-9560-00505683d611","carrier":{"id":168,"short_name":"ONE","official_name":"Ocean Network Express","scac":"ONEY"},"pol":{"id":14425,"name":"Lirquén","locode":"CLLQN","longitude":-72.983333,"latitude":-36.716667},"pod":{"id":15810,"name":"Mazatlan","locode":"MXMZT","longitude":-106.416667,"latitude":23.2},"etd":"2023-06-22T11:00+0000","eta":"2023-07-16T04:00+0000","etd_local":"2023-06-22T07:00-0400","eta_local":"2023-07-15T21:00-0700","legs":[{"pol":{"id":14425,"name":"Lirquén","locode":"CLLQN","longitude":-72.983333,"latitude":-36.716667},"pod":{"id":15770,"name":"Manzanillo","locode":"MXZLO","longitude":-104.333333,"latitude":19.05},"etd":"2023-06-22T11:00+0000","eta":"2023-07-05T12:00+0000","etd_local":"2023-06-22T07:00-0400","eta_local":"2023-07-05T06:00-0600","carrier_id":168,"service_id":12672,"service_name":"ASIA LATIN AMERICA EXPRESS SERVICE 2 - ALX2","service_code":"AX2","voyage_number":"316W","vessel":{"id":67856,"shipname":"MSC ELISA XIII","imo":9463059},"quality":0},{"pol":{"id":15770,"name":"Manzanillo","locode":"MXZLO","longitude":-104.333333,"latitude":19.05},"pod":{"id":15810,"name":"Mazatlan","locode":"MXMZT","longitude":-106.416667,"latitude":23.2},"etd":"2023-07-08T15:00+0000","eta":"2023-07-16T04:00+0000","etd_local":"2023-07-08T09:00-0600","eta_local":"2023-07-15T21:00-0700","carrier_id":168,"service_id":12028,"service_name":"MARGARITA NEO - EXPRESS SERVICE - MAREX","service_code":"MAR","voyage_number":"631W","vessel":{"id":56840,"shipname":"NYK LAURA","imo":9406752},"quality":0}],"alliance":{"id":999,"name":"Others"},"uuid_p2p":"eed352fa-1526-4c4c-8662-3d24a740365c","p2p_id":"CLLQNMXMZT","cyclosing":null,"transshipment_count":1,"transit_time":24},{"id":"79683c6e-0614-11ee-9560-00505683d611","carrier":{"id":168,"short_name":"ONE","official_name":"Ocean Network Express","scac":"ONEY"},"pol":{"id":14425,"name":"Lirquén","locode":"CLLQN","longitude":-72.983333,"latitude":-36.716667},"pod":{"id":15810,"name":"Mazatlan","locode":"MXMZT","longitude":-106.416667,"latitude":23.2},"etd":"2023-06-13T11:00+0000","eta":"2023-07-09T04:00+0000","etd_local":"2023-06-13T07:00-0400","eta_local":"2023-07-08T21:00-0700","legs":[{"pol":{"id":14425,"name":"Lirquén","locode":"CLLQN","longitude":-72.983333,"latitude":-36.716667},"pod":{"id":15770,"name":"Manzanillo","locode":"MXZLO","longitude":-104.333333,"latitude":19.05},"etd":"2023-06-13T11:00+0000","eta":"2023-06-28T12:00+0000","etd_local":"2023-06-13T07:00-0400","eta_local":"2023-06-28T06:00-0600","carrier_id":168,"service_id":12672,"service_name":"ASIA LATIN AMERICA EXPRESS SERVICE 2 - ALX2","service_code":"AX2","voyage_number":"315W","vessel":{"id":6875,"shipname":"MSC NATASHA XIII","imo":9463035},"quality":0},{"pol":{"id":15770,"name":"Manzanillo","locode":"MXZLO","longitude":-104.333333,"latitude":19.05},"pod":{"id":15810,"name":"Mazatlan","locode":"MXMZT","longitude":-106.416667,"latitude":23.2},"etd":"2023-07-01T15:00+0000","eta":"2023-07-09T04:00+0000","etd_local":"2023-07-01T09:00-0600","eta_local":"2023-07-08T21:00-0700","carrier_id":168,"service_id":12028,"service_name":"MARGARITA NEO - EXPRESS SERVICE - MAREX","service_code":"MAR","voyage_number":"334W","vessel":{"id":83072,"shipname":"FLEUR N","imo":9509138},"quality":0}],"alliance":{"id":999,"name":"Others"},"uuid_p2p":"b8639ab4-acde-40cf-83f5-f70980468abb","p2p_id":"CLLQNMXMZT","cyclosing":null,"transshipment_count":1,"transit_time":26},{"id":"79683480-0614-11ee-9560-00505683d611","carrier":{"id":168,"short_name":"ONE","official_name":"Ocean Network Express","scac":"ONEY"},"pol":{"id":14425,"name":"Lirquén","locode":"CLLQN","longitude":-72.983333,"latitude":-36.716667},"pod":{"id":15810,"name":"Mazatlan","locode":"MXMZT","longitude":-106.416667,"latitude":23.2},"etd":"2023-06-08T20:00+0000","eta":"2023-07-02T04:00+0000","etd_local":"2023-06-08T16:00-0400","eta_local":"2023-07-01T21:00-0700","legs":[{"pol":{"id":14425,"name":"Lirquén","locode":"CLLQN","longitude":-72.983333,"latitude":-36.716667},"pod":{"id":15770,"name":"Manzanillo","locode":"MXZLO","longitude":-104.333333,"latitude":19.05},"etd":"2023-06-08T20:00+0000","eta":"2023-06-20T08:30+0000","etd_local":"2023-06-08T16:00-0400","eta_local":"2023-06-20T02:30-0600","carrier_id":168,"service_id":12672,"service_name":"ASIA LATIN AMERICA EXPRESS SERVICE 2 - ALX2","service_code":"AX2","voyage_number":"314W","vessel":{"id":83662,"shipname":"MSC EMMA","imo":9463047},"quality":0},{"pol":{"id":15770,"name":"Manzanillo","locode":"MXZLO","longitude":-104.333333,"latitude":19.05},"pod":{"id":15810,"name":"Mazatlan","locode":"MXMZT","longitude":-106.416667,"latitude":23.2},"etd":"2023-06-24T18:00+0000","eta":"2023-07-02T04:00+0000","etd_local":"2023-06-24T12:00-0600","eta_local":"2023-07-01T21:00-0700","carrier_id":168,"service_id":12028,"service_name":"MARGARITA NEO - EXPRESS SERVICE - MAREX","service_code":"MAR","voyage_number":"174W","vessel":{"id":28927,"shipname":"NYK JOANNA","imo":9387449},"quality":0}],"alliance":{"id":999,"name":"Others"},"uuid_p2p":"03e1e19b-18a7-48e0-b9cb-ec680acb2ed5","p2p_id":"CLLQNMXMZT","cyclosing":null,"transshipment_count":1,"transit_time":24},{"id":"791cc91e-0614-11ee-9560-00505683d611","carrier":{"id":116,"short_name":"Hapag-Lloyd","official_name":"Hapag-Lloyd","scac":"HLCU"},"pol":{"id":14425,"name":"Lirquén","locode":"CLLQN","longitude":-72.983333,"latitude":-36.716667},"pod":{"id":15810,"name":"Mazatlan","locode":"MXMZT","longitude":-106.416667,"latitude":23.2},"etd":"2023-07-04T21:00+0000","eta":"2023-07-30T05:00+0000","etd_local":"2023-07-04T17:00-0400","eta_local":"2023-07-29T22:00-0700","legs":[{"pol":{"id":14425,"name":"Lirquén","locode":"CLLQN","longitude":-72.983333,"latitude":-36.716667},"pod":{"id":15770,"name":"Manzanillo","locode":"MXZLO","longitude":-104.333333,"latitude":19.05},"etd":"2023-07-04T21:00+0000","eta":"2023-07-20T13:00+0000","etd_local":"2023-07-04T17:00-0400","eta_local":"2023-07-20T07:00-0600","carrier_id":116,"service_id":5665,"service_name":"SOUTH AMERICA - ASIA - LOOP 2","service_code":"AN2","voyage_number":"FA327R","vessel":{"id":8142709,"shipname":"MSC JEWEL","imo":9842073},"quality":0},{"pol":{"id":15770,"name":"Manzanillo","locode":"MXZLO","longitude":-104.333333,"latitude":19.05},"pod":{"id":15810,"name":"Mazatlan","locode":"MXMZT","longitude":-106.416667,"latitude":23.2},"etd":"2023-07-22T15:00+0000","eta":"2023-07-30T05:00+0000","etd_local":"2023-07-22T09:00-0600","eta_local":"2023-07-29T22:00-0700","carrier_id":116,"service_id":5661,"service_name":"CALIFORNIA - CENTRAL AMERICA EXPRESS SERVICE","service_code":"CCE","voyage_number":"175W","vessel":{"id":28927,"shipname":"NYK JOANNA","imo":9387449},"quality":0}],"alliance":{"id":999,"name":"Others"},"uuid_p2p":"f64e7242-c550-450d-969b-6f89988c8222","p2p_id":"CLLQNMXMZT","cyclosing":null,"transshipment_count":1,"transit_time":26},{"id":"791cc144-0614-11ee-9560-00505683d611","carrier":{"id":116,"short_name":"Hapag-Lloyd","official_name":"Hapag-Lloyd","scac":"HLCU"},"pol":{"id":14425,"name":"Lirquén","locode":"CLLQN","longitude":-72.983333,"latitude":-36.716667},"pod":{"id":15810,"name":"Mazatlan","locode":"MXMZT","longitude":-106.416667,"latitude":23.2},"etd":"2023-06-27T11:00+0000","eta":"2023-07-24T05:00+0000","etd_local":"2023-06-27T07:00-0400","eta_local":"2023-07-23T22:00-0700","legs":[{"pol":{"id":14425,"name":"Lirquén","locode":"CLLQN","longitude":-72.983333,"latitude":-36.716667},"pod":{"id":15770,"name":"Manzanillo","locode":"MXZLO","longitude":-104.333333,"latitude":19.05},"etd":"2023-06-27T11:00+0000","eta":"2023-07-12T14:00+0000","etd_local":"2023-06-27T07:00-0400","eta_local":"2023-07-12T08:00-0600","carrier_id":116,"service_id":5665,"service_name":"SOUTH AMERICA - ASIA - LOOP 2","service_code":"AN2","voyage_number":"FA325R","vessel":{"id":9379754,"shipname":"MSC JOSSELINE","imo":9842061},"quality":0},{"pol":{"id":15770,"name":"Manzanillo","locode":"MXZLO","longitude":-104.333333,"latitude":19.05},"pod":{"id":15810,"name":"Mazatlan","locode":"MXMZT","longitude":-106.416667,"latitude":23.2},"etd":"2023-07-15T15:00+0000","eta":"2023-07-24T05:00+0000","etd_local":"2023-07-15T09:00-0600","eta_local":"2023-07-23T22:00-0700","carrier_id":116,"service_id":5661,"service_name":"CALIFORNIA - CENTRAL AMERICA EXPRESS SERVICE","service_code":"CCE","voyage_number":"404W","vessel":{"id":23729,"shipname":"NYK SILVIA","imo":9419656},"quality":0}],"alliance":{"id":999,"name":"Others"},"uuid_p2p":"c5f395f5-a558-4686-af87-794e9d48a2fb","p2p_id":"CLLQNMXMZT","cyclosing":null,"transshipment_count":1,"transit_time":27},{"id":"791cbce4-0614-11ee-9560-00505683d611","carrier":{"id":116,"short_name":"Hapag-Lloyd","official_name":"Hapag-Lloyd","scac":"HLCU"},"pol":{"id":14425,"name":"Lirquén","locode":"CLLQN","longitude":-72.983333,"latitude":-36.716667},"pod":{"id":15810,"name":"Mazatlan","locode":"MXMZT","longitude":-106.416667,"latitude":23.2},"etd":"2023-06-22T11:00+0000","eta":"2023-07-17T05:00+0000","etd_local":"2023-06-22T07:00-0400","eta_local":"2023-07-16T22:00-0700","legs":[{"pol":{"id":14425,"name":"Lirquén","locode":"CLLQN","longitude":-72.983333,"latitude":-36.716667},"pod":{"id":15770,"name":"Manzanillo","locode":"MXZLO","longitude":-104.333333,"latitude":19.05},"etd":"2023-06-22T11:00+0000","eta":"2023-07-05T14:00+0000","etd_local":"2023-06-22T07:00-0400","eta_local":"2023-07-05T08:00-0600","carrier_id":116,"service_id":5665,"service_name":"SOUTH AMERICA - ASIA - LOOP 2","service_code":"AN2","voyage_number":"FA324R","vessel":{"id":67856,"shipname":"MSC ELISA XIII","imo":9463059},"quality":0},{"pol":{"id":15770,"name":"Manzanillo","locode":"MXZLO","longitude":-104.333333,"latitude":19.05},"pod":{"id":15810,"name":"Mazatlan","locode":"MXMZT","longitude":-106.416667,"latitude":23.2},"etd":"2023-07-08T14:00+0000","eta":"2023-07-17T05:00+0000","etd_local":"2023-07-08T08:00-0600","eta_local":"2023-07-16T22:00-0700","carrier_id":116,"service_id":5661,"service_name":"CALIFORNIA - CENTRAL AMERICA EXPRESS SERVICE","service_code":"CCE","voyage_number":"631W","vessel":{"id":56840,"shipname":"NYK LAURA","imo":9406752},"quality":0}],"alliance":{"id":999,"name":"Others"},"uuid_p2p":"d38ef9be-3118-4d69-bc37-4a903aadcd53","p2p_id":"CLLQNMXMZT","cyclosing":null,"transshipment_count":1,"transit_time":25},{"id":"79684ad8-0614-11ee-9560-00505683d611","carrier":{"id":168,"short_name":"ONE","official_name":"Ocean Network Express","scac":"ONEY"},"pol":{"id":14425,"name":"Lirquén","locode":"CLLQN","longitude":-72.983333,"latitude":-36.716667},"pod":{"id":15810,"name":"Mazatlan","locode":"MXMZT","longitude":-106.416667,"latitude":23.2},"etd":"2023-07-04T12:00+0000","eta":"2023-07-30T04:00+0000","etd_local":"2023-07-04T08:00-0400","eta_local":"2023-07-29T21:00-0700","legs":[{"pol":{"id":14425,"name":"Lirquén","locode":"CLLQN","longitude":-72.983333,"latitude":-36.716667},"pod":{"id":15770,"name":"Manzanillo","locode":"MXZLO","longitude":-104.333333,"latitude":19.05},"etd":"2023-07-04T12:00+0000","eta":"2023-07-19T13:00+0000","etd_local":"2023-07-04T08:00-0400","eta_local":"2023-07-19T07:00-0600","carrier_id":168,"service_id":12672,"service_name":"ASIA LATIN AMERICA EXPRESS SERVICE 2 - ALX2","service_code":"AX2","voyage_number":"319W","vessel":{"id":8142709,"shipname":"MSC JEWEL","imo":9842073},"quality":0},{"pol":{"id":15770,"name":"Manzanillo","locode":"MXZLO","longitude":-104.333333,"latitude":19.05},"pod":{"id":15810,"name":"Mazatlan","locode":"MXMZT","longitude":-106.416667,"latitude":23.2},"etd":"2023-07-22T15:00+0000","eta":"2023-07-30T04:00+0000","etd_local":"2023-07-22T09:00-0600","eta_local":"2023-07-29T21:00-0700","carrier_id":168,"service_id":12028,"service_name":"MARGARITA NEO - EXPRESS SERVICE - MAREX","service_code":"MAR","voyage_number":"175W","vessel":{"id":28927,"shipname":"NYK JOANNA","imo":9387449},"quality":0}],"alliance":{"id":999,"name":"Others"},"uuid_p2p":"dcdb2253-99d7-4d2f-b8b2-97f4cf7369f1","p2p_id":"CLLQNMXMZT","cyclosing":null,"transshipment_count":1,"transit_time":26},{"id":"791cc568-0614-11ee-9560-00505683d611","carrier":{"id":116,"short_name":"Hapag-Lloyd","official_name":"Hapag-Lloyd","scac":"HLCU"},"pol":{"id":14425,"name":"Lirquén","locode":"CLLQN","longitude":-72.983333,"latitude":-36.716667},"pod":{"id":15810,"name":"Mazatlan","locode":"MXMZT","longitude":-106.416667,"latitude":23.2},"etd":"2023-07-04T01:00+0000","eta":"2023-07-30T05:00+0000","etd_local":"2023-07-03T21:00-0400","eta_local":"2023-07-29T22:00-0700","legs":[{"pol":{"id":14425,"name":"Lirquén","locode":"CLLQN","longitude":-72.983333,"latitude":-36.716667},"pod":{"id":15770,"name":"Manzanillo","locode":"MXZLO","longitude":-104.333333,"latitude":19.05},"etd":"2023-07-04T01:00+0000","eta":"2023-07-19T03:00+0000","etd_local":"2023-07-03T21:00-0400","eta_local":"2023-07-18T21:00-0600","carrier_id":116,"service_id":5665,"service_name":"SOUTH AMERICA - ASIA - LOOP 2","service_code":"AN2","voyage_number":"2318W","vessel":{"id":93376,"shipname":"SEASPAN BRAVO","imo":9685322},"quality":0},{"pol":{"id":15770,"name":"Manzanillo","locode":"MXZLO","longitude":-104.333333,"latitude":19.05},"pod":{"id":15810,"name":"Mazatlan","locode":"MXMZT","longitude":-106.416667,"latitude":23.2},"etd":"2023-07-22T15:00+0000","eta":"2023-07-30T05:00+0000","etd_local":"2023-07-22T09:00-0600","eta_local":"2023-07-29T22:00-0700","carrier_id":116,"service_id":5661,"service_name":"CALIFORNIA - CENTRAL AMERICA EXPRESS SERVICE","service_code":"CCE","voyage_number":"175W","vessel":{"id":28927,"shipname":"NYK JOANNA","imo":9387449},"quality":0}],"alliance":{"id":999,"name":"Others"},"uuid_p2p":"9dae2e56-d0fa-42e6-b2a3-d78a045c2e0f","p2p_id":"CLLQNMXMZT","cyclosing":null,"transshipment_count":1,"transit_time":26},{"id":"796848f8-0614-11ee-9560-00505683d611","carrier":{"id":168,"short_name":"ONE","official_name":"Ocean Network Express","scac":"ONEY"},"pol":{"id":14425,"name":"Lirquén","locode":"CLLQN","longitude":-72.983333,"latitude":-36.716667},"pod":{"id":15810,"name":"Mazatlan","locode":"MXMZT","longitude":-106.416667,"latitude":23.2},"etd":"2023-07-04T01:00+0000","eta":"2023-07-30T04:00+0000","etd_local":"2023-07-03T21:00-0400","eta_local":"2023-07-29T21:00-0700","legs":[{"pol":{"id":14425,"name":"Lirquén","locode":"CLLQN","longitude":-72.983333,"latitude":-36.716667},"pod":{"id":15770,"name":"Manzanillo","locode":"MXZLO","longitude":-104.333333,"latitude":19.05},"etd":"2023-07-04T01:00+0000","eta":"2023-07-19T02:00+0000","etd_local":"2023-07-03T21:00-0400","eta_local":"2023-07-18T20:00-0600","carrier_id":168,"service_id":12672,"service_name":"ASIA LATIN AMERICA EXPRESS SERVICE 2 - ALX2","service_code":"AX2","voyage_number":"2318W","vessel":{"id":93376,"shipname":"SEASPAN BRAVO","imo":9685322},"quality":0},{"pol":{"id":15770,"name":"Manzanillo","locode":"MXZLO","longitude":-104.333333,"latitude":19.05},"pod":{"id":15810,"name":"Mazatlan","locode":"MXMZT","longitude":-106.416667,"latitude":23.2},"etd":"2023-07-22T15:00+0000","eta":"2023-07-30T04:00+0000","etd_local":"2023-07-22T09:00-0600","eta_local":"2023-07-29T21:00-0700","carrier_id":168,"service_id":12028,"service_name":"MARGARITA NEO - EXPRESS SERVICE - MAREX","service_code":"MAR","voyage_number":"175W","vessel":{"id":28927,"shipname":"NYK JOANNA","imo":9387449},"quality":0}],"alliance":{"id":999,"name":"Others"},"uuid_p2p":"d778618d-5630-411f-bd0a-3c9b62551a56","p2p_id":"CLLQNMXMZT","cyclosing":null,"transshipment_count":1,"transit_time":26}],"completed":true,"etd":"2023-05-25","eta":null,"weeks":6,"allroutes":false,"carrier":null,"direct":false,"num_results":11}