{"handle":"7b83ba07-127e-42e4-aa95-fea31d98209e","p2p_id":"CLSAIPECLL","pol":14470,"pod":14950,"results":[{"id":"8134778c-0614-11ee-9560-00505683d611","carrier":{"id":93,"short_name":"Aliança","official_name":"Aliança Navegação e Logística","scac":"ALIU"},"pol":{"id":14470,"name":"San Antonio","locode":"CLSAI","longitude":-71.616667,"latitude":-33.583333},"pod":{"id":14950,"name":"Puerto Del Callao","locode":"PECLL","longitude":-77.15,"latitude":-12.05},"etd":"2023-06-11T03:00+0000","eta":"2023-06-16T17:00+0000","etd_local":"2023-06-10T23:00-0400","eta_local":"2023-06-16T12:00-0500","legs":[{"pol":{"id":14470,"name":"San Antonio","locode":"CLSAI","longitude":-71.616667,"latitude":-33.583333},"pod":{"id":14950,"name":"Puerto Del Callao","locode":"PECLL","longitude":-77.15,"latitude":-12.05},"etd":"2023-06-11T03:00+0000","eta":"2023-06-16T17:00+0000","etd_local":"2023-06-10T23:00-0400","eta_local":"2023-06-16T12:00-0500","carrier_id":93,"service_id":2090,"service_name":"CONOSUR SERVICE","service_code":"ABAC","voyage_number":"321W","vessel":{"id":11001,"shipname":"ANTOFAGASTA EXPRESS","imo":9612789},"quality":0}],"alliance":{"id":999,"name":"Others"},"uuid_p2p":"091744ac-1331-472b-b056-b91d47c875ea","p2p_id":"CLSAIPECLL","cyclosing":null,"transshipment_count":0,"transit_time":5},{"id":"83737b1a-0614-11ee-9560-00505683d611","carrier":{"id":114,"short_name":"Hamburg Süd","official_name":"Hamburg Süd","scac":"SUDU"},"pol":{"id":14470,"name":"San Antonio","locode":"CLSAI","longitude":-71.616667,"latitude":-33.583333},"pod":{"id":14950,"name":"Puerto Del Callao","locode":"PECLL","longitude":-77.15,"latitude":-12.05},"etd":"2023-07-02T03:00+0000","eta":"2023-07-07T17:00+0000","etd_local":"2023-07-01T23:00-0400","eta_local":"2023-07-07T12:00-0500","legs":[{"pol":{"id":14470,"name":"San Antonio","locode":"CLSAI","longitude":-71.616667,"latitude":-33.583333},"pod":{"id":14950,"name":"Puerto Del Callao","locode":"PECLL","longitude":-77.15,"latitude":-12.05},"etd":"2023-07-02T03:00+0000","eta":"2023-07-07T17:00+0000","etd_local":"2023-07-01T23:00-0400","eta_local":"2023-07-07T12:00-0500","carrier_id":114,"service_id":1194,"service_name":"CONOSUR SERVICE","service_code":"ABAC","voyage_number":"324W","vessel":{"id":52910,"shipname":"SAN ANTONIO EXPRESS","imo":9612777},"quality":0}],"alliance":{"id":999,"name":"Others"},"uuid_p2p":"491365ce-a1ce-4359-ab0e-2acfa31eae5e","p2p_id":"CLSAIPECLL","cyclosing":null,"transshipment_count":0,"transit_time":5},{"id":"83e94a2a-0614-11ee-9560-00505683d611","carrier":{"id":116,"short_name":"Hapag-Lloyd","official_name":"Hapag-Lloyd","scac":"HLCU"},"pol":{"id":14470,"name":"San Antonio","locode":"CLSAI","longitude":-71.616667,"latitude":-33.583333},"pod":{"id":14950,"name":"Puerto Del Callao","locode":"PECLL","longitude":-77.15,"latitude":-12.05},"etd":"2023-06-10T02:00+0000","eta":"2023-06-13T04:00+0000","etd_local":"2023-06-09T22:00-0400","eta_local":"2023-06-12T23:00-0500","legs":[{"pol":{"id":14470,"name":"San Antonio","locode":"CLSAI","longitude":-71.616667,"latitude":-33.583333},"pod":{"id":14950,"name":"Puerto Del Callao","locode":"PECLL","longitude":-77.15,"latitude":-12.05},"etd":"2023-06-10T02:00+0000","eta":"2023-06-13T04:00+0000","etd_local":"2023-06-09T22:00-0400","eta_local":"2023-06-12T23:00-0500","carrier_id":116,"service_id":4312,"service_name":"SOUTH AMERICA WEST COAST SERVICE","service_code":"SWX","voyage_number":"3218N","vessel":{"id":3807632,"shipname":"COSCO SHIPPING VOLGA","imo":9731925},"quality":0}],"alliance":{"id":999,"name":"Others"},"uuid_p2p":"c5f42e15-21ee-41f3-a07d-1142c3f1f592","p2p_id":"CLSAIPECLL","cyclosing":null,"transshipment_count":0,"transit_time":3},{"id":"83e9619a-0614-11ee-9560-00505683d611","carrier":{"id":116,"short_name":"Hapag-Lloyd","official_name":"Hapag-Lloyd","scac":"HLCU"},"pol":{"id":14470,"name":"San Antonio","locode":"CLSAI","longitude":-71.616667,"latitude":-33.583333},"pod":{"id":14950,"name":"Puerto Del Callao","locode":"PECLL","longitude":-77.15,"latitude":-12.05},"etd":"2023-06-24T03:00+0000","eta":"2023-06-27T02:00+0000","etd_local":"2023-06-23T23:00-0400","eta_local":"2023-06-26T21:00-0500","legs":[{"pol":{"id":14470,"name":"San Antonio","locode":"CLSAI","longitude":-71.616667,"latitude":-33.583333},"pod":{"id":14950,"name":"Puerto Del Callao","locode":"PECLL","longitude":-77.15,"latitude":-12.05},"etd":"2023-06-24T03:00+0000","eta":"2023-06-27T02:00+0000","etd_local":"2023-06-23T23:00-0400","eta_local":"2023-06-26T21:00-0500","carrier_id":116,"service_id":4312,"service_name":"SOUTH AMERICA WEST COAST SERVICE","service_code":"SWX","voyage_number":"3220N","vessel":{"id":3520932,"shipname":"VALPARAISO EXPRESS","imo":9777589},"quality":0}],"alliance":{"id":999,"name":"Others"},"uuid_p2p":"b379080c-4769-4e15-9ac3-38bb597cdcbe","p2p_id":"CLSAIPECLL","cyclosing":null,"transshipment_count":0,"transit_time":3},{"id":"83e9851c-0614-11ee-9560-00505683d611","carrier":{"id":116,"short_name":"Hapag-Lloyd","official_name":"Hapag-Lloyd","scac":"HLCU"},"pol":{"id":14470,"name":"San Antonio","locode":"CLSAI","longitude":-71.616667,"latitude":-33.583333},"pod":{"id":14950,"name":"Puerto Del Callao","locode":"PECLL","longitude":-77.15,"latitude":-12.05},"etd":"2023-07-01T03:00+0000","eta":"2023-07-04T04:00+0000","etd_local":"2023-06-30T23:00-0400","eta_local":"2023-07-03T23:00-0500","legs":[{"pol":{"id":14470,"name":"San Antonio","locode":"CLSAI","longitude":-71.616667,"latitude":-33.583333},"pod":{"id":14950,"name":"Puerto Del Callao","locode":"PECLL","longitude":-77.15,"latitude":-12.05},"etd":"2023-07-01T03:00+0000","eta":"2023-07-04T04:00+0000","etd_local":"2023-06-30T23:00-0400","eta_local":"2023-07-03T23:00-0500","carrier_id":116,"service_id":4312,"service_name":"SOUTH AMERICA WEST COAST SERVICE","service_code":"SWX","voyage_number":"3221N","vessel":{"id":5828076,"shipname":"SALVADOR EXPRESS","imo":9793894},"quality":0}],"alliance":{"id":999,"name":"Others"},"uuid_p2p":"2f1b69c3-1b1c-4178-a6c9-ac34e93f9711","p2p_id":"CLSAIPECLL","cyclosing":null,"transshipment_count":0,"transit_time":3},{"id":"83ea0f14-0614-11ee-9560-00505683d611","carrier":{"id":116,"short_name":"Hapag-Lloyd","official_name":"Hapag-Lloyd","scac":"HLCU"},"pol":{"id":14470,"name":"San Antonio","locode":"CLSAI","longitude":-71.616667,"latitude":-33.583333},"pod":{"id":14950,"name":"Puerto Del Callao","locode":"PECLL","longitude":-77.15,"latitude":-12.05},"etd":"2023-06-17T03:00+0000","eta":"2023-06-20T04:00+0000","etd_local":"2023-06-16T23:00-0400","eta_local":"2023-06-19T23:00-0500","legs":[{"pol":{"id":14470,"name":"San Antonio","locode":"CLSAI","longitude":-71.616667,"latitude":-33.583333},"pod":{"id":14950,"name":"Puerto Del Callao","locode":"PECLL","longitude":-77.15,"latitude":-12.05},"etd":"2023-06-17T03:00+0000","eta":"2023-06-20T04:00+0000","etd_local":"2023-06-16T23:00-0400","eta_local":"2023-06-19T23:00-0500","carrier_id":116,"service_id":4312,"service_name":"SOUTH AMERICA WEST COAST SERVICE","service_code":"SWX","voyage_number":"3219N","vessel":{"id":5764340,"shipname":"CMA CGM ESTELLE","imo":9729116},"quality":0}],"alliance":{"id":999,"name":"Others"},"uuid_p2p":"9555235e-4b03-480d-95f7-273e39b78161","p2p_id":"CLSAIPECLL","cyclosing":null,"transshipment_count":0,"transit_time":3},{"id":"846e2222-0614-11ee-9560-00505683d611","carrier":{"id":122,"short_name":"Maersk","official_name":"Maersk Line","scac":"MAEU"},"pol":{"id":14470,"name":"San Antonio","locode":"CLSAI","longitude":-71.616667,"latitude":-33.583333},"pod":{"id":14950,"name":"Puerto Del Callao","locode":"PECLL","longitude":-77.15,"latitude":-12.05},"etd":"2023-06-15T05:30+0000","eta":"2023-06-24T04:00+0000","etd_local":"2023-06-15T01:30-0400","eta_local":"2023-06-23T23:00-0500","legs":[{"pol":{"id":14470,"name":"San Antonio","locode":"CLSAI","longitude":-71.616667,"latitude":-33.583333},"pod":{"id":14950,"name":"Puerto Del Callao","locode":"PECLL","longitude":-77.15,"latitude":-12.05},"etd":"2023-06-15T05:30+0000","eta":"2023-06-24T04:00+0000","etd_local":"2023-06-15T01:30-0400","eta_local":"2023-06-23T23:00-0500","carrier_id":122,"service_id":10096,"service_name":"ATACAMA SERVICE","service_code":"ATACAMA","voyage_number":"323N","vessel":{"id":1804974,"shipname":"POLAR COLOMBIA","imo":9786762},"quality":0}],"alliance":{"id":999,"name":"Others"},"uuid_p2p":"3550ea4d-babb-4078-ae5e-d5dc1f8f3f01","p2p_id":"CLSAIPECLL","cyclosing":"2023-06-13T00:00+0000","transshipment_count":0,"transit_time":9},{"id":"846e2fec-0614-11ee-9560-00505683d611","carrier":{"id":122,"short_name":"Maersk","official_name":"Maersk Line","scac":"MAEU"},"pol":{"id":14470,"name":"San Antonio","locode":"CLSAI","longitude":-71.616667,"latitude":-33.583333},"pod":{"id":14950,"name":"Puerto Del Callao","locode":"PECLL","longitude":-77.15,"latitude":-12.05},"etd":"2023-06-22T05:30+0000","eta":"2023-07-01T04:00+0000","etd_local":"2023-06-22T01:30-0400","eta_local":"2023-06-30T23:00-0500","legs":[{"pol":{"id":14470,"name":"San Antonio","locode":"CLSAI","longitude":-71.616667,"latitude":-33.583333},"pod":{"id":14950,"name":"Puerto Del Callao","locode":"PECLL","longitude":-77.15,"latitude":-12.05},"etd":"2023-06-22T05:30+0000","eta":"2023-07-01T04:00+0000","etd_local":"2023-06-22T01:30-0400","eta_local":"2023-06-30T23:00-0500","carrier_id":122,"service_id":10096,"service_name":"ATACAMA SERVICE","service_code":"ATACAMA","voyage_number":"324N","vessel":{"id":29899,"shipname":"JPO LIBRA","imo":9297840},"quality":0}],"alliance":{"id":999,"name":"Others"},"uuid_p2p":"7db90030-ecb6-4c4d-aca8-79bb0b0d732b","p2p_id":"CLSAIPECLL","cyclosing":null,"transshipment_count":0,"transit_time":9},{"id":"846e3802-0614-11ee-9560-00505683d611","carrier":{"id":122,"short_name":"Maersk","official_name":"Maersk Line","scac":"MAEU"},"pol":{"id":14470,"name":"San Antonio","locode":"CLSAI","longitude":-71.616667,"latitude":-33.583333},"pod":{"id":14950,"name":"Puerto Del Callao","locode":"PECLL","longitude":-77.15,"latitude":-12.05},"etd":"2023-06-29T05:30+0000","eta":"2023-07-08T04:00+0000","etd_local":"2023-06-29T01:30-0400","eta_local":"2023-07-07T23:00-0500","legs":[{"pol":{"id":14470,"name":"San Antonio","locode":"CLSAI","longitude":-71.616667,"latitude":-33.583333},"pod":{"id":14950,"name":"Puerto Del Callao","locode":"PECLL","longitude":-77.15,"latitude":-12.05},"etd":"2023-06-29T05:30+0000","eta":"2023-07-08T04:00+0000","etd_local":"2023-06-29T01:30-0400","eta_local":"2023-07-07T23:00-0500","carrier_id":122,"service_id":10096,"service_name":"ATACAMA SERVICE","service_code":"ATACAMA","voyage_number":"325N","vessel":{"id":5712864,"shipname":"POLAR ARGENTINA","imo":9797204},"quality":0}],"alliance":{"id":999,"name":"Others"},"uuid_p2p":"8ae6209c-7635-4d72-8b2d-c7689e3360ee","p2p_id":"CLSAIPECLL","cyclosing":null,"transshipment_count":0,"transit_time":9},{"id":"846e3f5a-0614-11ee-9560-00505683d611","carrier":{"id":122,"short_name":"Maersk","official_name":"Maersk Line","scac":"MAEU"},"pol":{"id":14470,"name":"San Antonio","locode":"CLSAI","longitude":-71.616667,"latitude":-33.583333},"pod":{"id":14950,"name":"Puerto Del Callao","locode":"PECLL","longitude":-77.15,"latitude":-12.05},"etd":"2023-07-06T05:30+0000","eta":"2023-07-15T04:00+0000","etd_local":"2023-07-06T01:30-0400","eta_local":"2023-07-14T23:00-0500","legs":[{"pol":{"id":14470,"name":"San Antonio","locode":"CLSAI","longitude":-71.616667,"latitude":-33.583333},"pod":{"id":14950,"name":"Puerto Del Callao","locode":"PECLL","longitude":-77.15,"latitude":-12.05},"etd":"2023-07-06T05:30+0000","eta":"2023-07-15T04:00+0000","etd_local":"2023-07-06T01:30-0400","eta_local":"2023-07-14T23:00-0500","carrier_id":122,"service_id":10096,"service_name":"ATACAMA SERVICE","service_code":"ATACAMA","voyage_number":"326N","vessel":{"id":5224588,"shipname":"POLAR PERU","imo":9797199},"quality":0}],"alliance":{"id":999,"name":"Others"},"uuid_p2p":"d3b93f70-966c-4baf-b68a-107390cec37f","p2p_id":"CLSAIPECLL","cyclosing":null,"transshipment_count":0,"transit_time":9},{"id":"84851400-0614-11ee-9560-00505683d611","carrier":{"id":126,"short_name":"OOCL","official_name":"Orient Overseas Container Line","scac":"OOLU"},"pol":{"id":14470,"name":"San Antonio","locode":"CLSAI","longitude":-71.616667,"latitude":-33.583333},"pod":{"id":14950,"name":"Puerto Del Callao","locode":"PECLL","longitude":-77.15,"latitude":-12.05},"etd":"2023-06-10T02:00+0000","eta":"2023-06-13T04:00+0000","etd_local":"2023-06-09T22:00-0400","eta_local":"2023-06-12T23:00-0500","legs":[{"pol":{"id":14470,"name":"San Antonio","locode":"CLSAI","longitude":-71.616667,"latitude":-33.583333},"pod":{"id":14950,"name":"Puerto Del Callao","locode":"PECLL","longitude":-77.15,"latitude":-12.05},"etd":"2023-06-10T02:00+0000","eta":"2023-06-13T04:00+0000","etd_local":"2023-06-09T22:00-0400","eta_local":"2023-06-12T23:00-0500","carrier_id":126,"service_id":23905,"service_name":"EUROPE - LATIN AMERICA SERVICE","service_code":"EWX","voyage_number":"3218N","vessel":{"id":3807632,"shipname":"COSCO SHIPPING VOLGA","imo":9731925},"quality":0}],"alliance":{"id":999,"name":"Others"},"uuid_p2p":"ee518e71-98b7-423d-a21f-352d26bf1652","p2p_id":"CLSAIPECLL","cyclosing":null,"transshipment_count":0,"transit_time":3},{"id":"84851bee-0614-11ee-9560-00505683d611","carrier":{"id":126,"short_name":"OOCL","official_name":"Orient Overseas Container Line","scac":"OOLU"},"pol":{"id":14470,"name":"San Antonio","locode":"CLSAI","longitude":-71.616667,"latitude":-33.583333},"pod":{"id":14950,"name":"Puerto Del Callao","locode":"PECLL","longitude":-77.15,"latitude":-12.05},"etd":"2023-06-17T03:00+0000","eta":"2023-06-20T04:00+0000","etd_local":"2023-06-16T23:00-0400","eta_local":"2023-06-19T23:00-0500","legs":[{"pol":{"id":14470,"name":"San Antonio","locode":"CLSAI","longitude":-71.616667,"latitude":-33.583333},"pod":{"id":14950,"name":"Puerto Del Callao","locode":"PECLL","longitude":-77.15,"latitude":-12.05},"etd":"2023-06-17T03:00+0000","eta":"2023-06-20T04:00+0000","etd_local":"2023-06-16T23:00-0400","eta_local":"2023-06-19T23:00-0500","carrier_id":126,"service_id":23905,"service_name":"EUROPE - LATIN AMERICA SERVICE","service_code":"EWX","voyage_number":"0WCT5N1MA","vessel":{"id":5764340,"shipname":"CMA CGM ESTELLE","imo":9729116},"quality":0}],"alliance":{"id":999,"name":"Others"},"uuid_p2p":"bd725c78-cf6b-43f8-92d0-3a686b6cd029","p2p_id":"CLSAIPECLL","cyclosing":null,"transshipment_count":0,"transit_time":3},{"id":"84851e82-0614-11ee-9560-00505683d611","carrier":{"id":126,"short_name":"OOCL","official_name":"Orient Overseas Container Line","scac":"OOLU"},"pol":{"id":14470,"name":"San Antonio","locode":"CLSAI","longitude":-71.616667,"latitude":-33.583333},"pod":{"id":14950,"name":"Puerto Del Callao","locode":"PECLL","longitude":-77.15,"latitude":-12.05},"etd":"2023-06-24T03:00+0000","eta":"2023-06-27T04:00+0000","etd_local":"2023-06-23T23:00-0400","eta_local":"2023-06-26T23:00-0500","legs":[{"pol":{"id":14470,"name":"San Antonio","locode":"CLSAI","longitude":-71.616667,"latitude":-33.583333},"pod":{"id":14950,"name":"Puerto Del Callao","locode":"PECLL","longitude":-77.15,"latitude":-12.05},"etd":"2023-06-24T03:00+0000","eta":"2023-06-27T04:00+0000","etd_local":"2023-06-23T23:00-0400","eta_local":"2023-06-26T23:00-0500","carrier_id":126,"service_id":23905,"service_name":"EUROPE - LATIN AMERICA SERVICE","service_code":"EWX","voyage_number":"3220N","vessel":{"id":3520932,"shipname":"VALPARAISO EXPRESS","imo":9777589},"quality":0}],"alliance":{"id":999,"name":"Others"},"uuid_p2p":"ea8c1828-f579-43b5-af30-da36a5172520","p2p_id":"CLSAIPECLL","cyclosing":null,"transshipment_count":0,"transit_time":3},{"id":"848520b2-0614-11ee-9560-00505683d611","carrier":{"id":126,"short_name":"OOCL","official_name":"Orient Overseas Container Line","scac":"OOLU"},"pol":{"id":14470,"name":"San Antonio","locode":"CLSAI","longitude":-71.616667,"latitude":-33.583333},"pod":{"id":14950,"name":"Puerto Del Callao","locode":"PECLL","longitude":-77.15,"latitude":-12.05},"etd":"2023-07-01T03:00+0000","eta":"2023-07-04T04:00+0000","etd_local":"2023-06-30T23:00-0400","eta_local":"2023-07-03T23:00-0500","legs":[{"pol":{"id":14470,"name":"San Antonio","locode":"CLSAI","longitude":-71.616667,"latitude":-33.583333},"pod":{"id":14950,"name":"Puerto Del Callao","locode":"PECLL","longitude":-77.15,"latitude":-12.05},"etd":"2023-07-01T03:00+0000","eta":"2023-07-04T04:00+0000","etd_local":"2023-06-30T23:00-0400","eta_local":"2023-07-03T23:00-0500","carrier_id":126,"service_id":23905,"service_name":"EUROPE - LATIN AMERICA SERVICE","service_code":"EWX","voyage_number":"3221N","vessel":{"id":28138689,"shipname":"BUENOS AIRES EXPRESS","imo":9932476},"quality":0}],"alliance":{"id":999,"name":"Others"},"uuid_p2p":"a18b82a2-fad2-4891-a5dd-313f9f73be74","p2p_id":"CLSAIPECLL","cyclosing":null,"transshipment_count":0,"transit_time":3},{"id":"84b76522-0614-11ee-9560-00505683d611","carrier":{"id":155,"short_name":"Sealand Americas","official_name":"Sealand Americas","scac":"SEAU"},"pol":{"id":14470,"name":"San Antonio","locode":"CLSAI","longitude":-71.616667,"latitude":-33.583333},"pod":{"id":14950,"name":"Puerto Del Callao","locode":"PECLL","longitude":-77.15,"latitude":-12.05},"etd":"2023-06-18T03:00+0000","eta":"2023-06-23T17:00+0000","etd_local":"2023-06-17T23:00-0400","eta_local":"2023-06-23T12:00-0500","legs":[{"pol":{"id":14470,"name":"San Antonio","locode":"CLSAI","longitude":-71.616667,"latitude":-33.583333},"pod":{"id":14950,"name":"Puerto Del Callao","locode":"PECLL","longitude":-77.15,"latitude":-12.05},"etd":"2023-06-18T03:00+0000","eta":"2023-06-23T17:00+0000","etd_local":"2023-06-17T23:00-0400","eta_local":"2023-06-23T12:00-0500","carrier_id":155,"service_id":13943,"service_name":"CONOSUR SERVICE","service_code":"ABAC","voyage_number":"322W","vessel":{"id":5712864,"shipname":"POLAR ARGENTINA","imo":9797204},"quality":0}],"alliance":{"id":999,"name":"Others"},"uuid_p2p":"068ec702-f8c5-4ff6-8278-6ba023d4b99f","p2p_id":"CLSAIPECLL","cyclosing":null,"transshipment_count":0,"transit_time":5},{"id":"84b76f18-0614-11ee-9560-00505683d611","carrier":{"id":155,"short_name":"Sealand Americas","official_name":"Sealand Americas","scac":"SEAU"},"pol":{"id":14470,"name":"San Antonio","locode":"CLSAI","longitude":-71.616667,"latitude":-33.583333},"pod":{"id":14950,"name":"Puerto Del Callao","locode":"PECLL","longitude":-77.15,"latitude":-12.05},"etd":"2023-06-25T03:00+0000","eta":"2023-06-30T15:00+0000","etd_local":"2023-06-24T23:00-0400","eta_local":"2023-06-30T10:00-0500","legs":[{"pol":{"id":14470,"name":"San Antonio","locode":"CLSAI","longitude":-71.616667,"latitude":-33.583333},"pod":{"id":14950,"name":"Puerto Del Callao","locode":"PECLL","longitude":-77.15,"latitude":-12.05},"etd":"2023-06-25T03:00+0000","eta":"2023-06-30T15:00+0000","etd_local":"2023-06-24T23:00-0400","eta_local":"2023-06-30T10:00-0500","carrier_id":155,"service_id":13943,"service_name":"CONOSUR SERVICE","service_code":"ABAC","voyage_number":"323W","vessel":{"id":15022,"shipname":"AMSTERDAM EXPRESS","imo":9193317},"quality":0}],"alliance":{"id":999,"name":"Others"},"uuid_p2p":"5511fc24-ed82-41dd-831d-273e4dc356a8","p2p_id":"CLSAIPECLL","cyclosing":null,"transshipment_count":0,"transit_time":5},{"id":"84b77828-0614-11ee-9560-00505683d611","carrier":{"id":155,"short_name":"Sealand Americas","official_name":"Sealand Americas","scac":"SEAU"},"pol":{"id":14470,"name":"San Antonio","locode":"CLSAI","longitude":-71.616667,"latitude":-33.583333},"pod":{"id":14950,"name":"Puerto Del Callao","locode":"PECLL","longitude":-77.15,"latitude":-12.05},"etd":"2023-07-02T03:00+0000","eta":"2023-07-07T17:00+0000","etd_local":"2023-07-01T23:00-0400","eta_local":"2023-07-07T12:00-0500","legs":[{"pol":{"id":14470,"name":"San Antonio","locode":"CLSAI","longitude":-71.616667,"latitude":-33.583333},"pod":{"id":14950,"name":"Puerto Del Callao","locode":"PECLL","longitude":-77.15,"latitude":-12.05},"etd":"2023-07-02T03:00+0000","eta":"2023-07-07T17:00+0000","etd_local":"2023-07-01T23:00-0400","eta_local":"2023-07-07T12:00-0500","carrier_id":155,"service_id":13943,"service_name":"CONOSUR SERVICE","service_code":"ABAC","voyage_number":"324W","vessel":{"id":52910,"shipname":"SAN ANTONIO EXPRESS","imo":9612777},"quality":0}],"alliance":{"id":999,"name":"Others"},"uuid_p2p":"0263322b-4f85-41ec-b19f-8804e14d5704","p2p_id":"CLSAIPECLL","cyclosing":null,"transshipment_count":0,"transit_time":5},{"id":"8373695e-0614-11ee-9560-00505683d611","carrier":{"id":114,"short_name":"Hamburg Süd","official_name":"Hamburg Süd","scac":"SUDU"},"pol":{"id":14470,"name":"San Antonio","locode":"CLSAI","longitude":-71.616667,"latitude":-33.583333},"pod":{"id":14950,"name":"Puerto Del Callao","locode":"PECLL","longitude":-77.15,"latitude":-12.05},"etd":"2023-06-25T03:00+0000","eta":"2023-06-30T15:00+0000","etd_local":"2023-06-24T23:00-0400","eta_local":"2023-06-30T10:00-0500","legs":[{"pol":{"id":14470,"name":"San Antonio","locode":"CLSAI","longitude":-71.616667,"latitude":-33.583333},"pod":{"id":14950,"name":"Puerto Del Callao","locode":"PECLL","longitude":-77.15,"latitude":-12.05},"etd":"2023-06-25T03:00+0000","eta":"2023-06-30T15:00+0000","etd_local":"2023-06-24T23:00-0400","eta_local":"2023-06-30T10:00-0500","carrier_id":114,"service_id":1194,"service_name":"CONOSUR SERVICE","service_code":"ABAC","voyage_number":"323W","vessel":{"id":15022,"shipname":"AMSTERDAM EXPRESS","imo":9193317},"quality":0}],"alliance":{"id":999,"name":"Others"},"uuid_p2p":"c613c35f-64f1-44ea-b3ca-91f93dfd1530","p2p_id":"CLSAIPECLL","cyclosing":null,"transshipment_count":0,"transit_time":5},{"id":"8373559a-0614-11ee-9560-00505683d611","carrier":{"id":114,"short_name":"Hamburg Süd","official_name":"Hamburg Süd","scac":"SUDU"},"pol":{"id":14470,"name":"San Antonio","locode":"CLSAI","longitude":-71.616667,"latitude":-33.583333},"pod":{"id":14950,"name":"Puerto Del Callao","locode":"PECLL","longitude":-77.15,"latitude":-12.05},"etd":"2023-06-18T03:00+0000","eta":"2023-06-23T17:00+0000","etd_local":"2023-06-17T23:00-0400","eta_local":"2023-06-23T12:00-0500","legs":[{"pol":{"id":14470,"name":"San Antonio","locode":"CLSAI","longitude":-71.616667,"latitude":-33.583333},"pod":{"id":14950,"name":"Puerto Del Callao","locode":"PECLL","longitude":-77.15,"latitude":-12.05},"etd":"2023-06-18T03:00+0000","eta":"2023-06-23T17:00+0000","etd_local":"2023-06-17T23:00-0400","eta_local":"2023-06-23T12:00-0500","carrier_id":114,"service_id":1194,"service_name":"CONOSUR SERVICE","service_code":"ABAC","voyage_number":"322W","vessel":{"id":5712864,"shipname":"POLAR ARGENTINA","imo":9797204},"quality":0}],"alliance":{"id":999,"name":"Others"},"uuid_p2p":"15ff26e1-968f-4909-88ef-f5be566e623d","p2p_id":"CLSAIPECLL","cyclosing":null,"transshipment_count":0,"transit_time":5},{"id":"81347e62-0614-11ee-9560-00505683d611","carrier":{"id":93,"short_name":"Aliança","official_name":"Aliança Navegação e Logística","scac":"ALIU"},"pol":{"id":14470,"name":"San Antonio","locode":"CLSAI","longitude":-71.616667,"latitude":-33.583333},"pod":{"id":14950,"name":"Puerto Del Callao","locode":"PECLL","longitude":-77.15,"latitude":-12.05},"etd":"2023-06-18T03:00+0000","eta":"2023-06-23T17:00+0000","etd_local":"2023-06-17T23:00-0400","eta_local":"2023-06-23T12:00-0500","legs":[{"pol":{"id":14470,"name":"San Antonio","locode":"CLSAI","longitude":-71.616667,"latitude":-33.583333},"pod":{"id":14950,"name":"Puerto Del Callao","locode":"PECLL","longitude":-77.15,"latitude":-12.05},"etd":"2023-06-18T03:00+0000","eta":"2023-06-23T17:00+0000","etd_local":"2023-06-17T23:00-0400","eta_local":"2023-06-23T12:00-0500","carrier_id":93,"service_id":2090,"service_name":"CONOSUR SERVICE","service_code":"ABAC","voyage_number":"322W","vessel":{"id":5712864,"shipname":"POLAR ARGENTINA","imo":9797204},"quality":0}],"alliance":{"id":999,"name":"Others"},"uuid_p2p":"1e7db492-231e-4b52-81b9-92244378591a","p2p_id":"CLSAIPECLL","cyclosing":null,"transshipment_count":0,"transit_time":5},{"id":"813480d8-0614-11ee-9560-00505683d611","carrier":{"id":93,"short_name":"Aliança","official_name":"Aliança Navegação e Logística","scac":"ALIU"},"pol":{"id":14470,"name":"San Antonio","locode":"CLSAI","longitude":-71.616667,"latitude":-33.583333},"pod":{"id":14950,"name":"Puerto Del Callao","locode":"PECLL","longitude":-77.15,"latitude":-12.05},"etd":"2023-06-25T03:00+0000","eta":"2023-06-30T15:00+0000","etd_local":"2023-06-24T23:00-0400","eta_local":"2023-06-30T10:00-0500","legs":[{"pol":{"id":14470,"name":"San Antonio","locode":"CLSAI","longitude":-71.616667,"latitude":-33.583333},"pod":{"id":14950,"name":"Puerto Del Callao","locode":"PECLL","longitude":-77.15,"latitude":-12.05},"etd":"2023-06-25T03:00+0000","eta":"2023-06-30T15:00+0000","etd_local":"2023-06-24T23:00-0400","eta_local":"2023-06-30T10:00-0500","carrier_id":93,"service_id":2090,"service_name":"CONOSUR SERVICE","service_code":"ABAC","voyage_number":"323W","vessel":{"id":15022,"shipname":"AMSTERDAM EXPRESS","imo":9193317},"quality":0}],"alliance":{"id":999,"name":"Others"},"uuid_p2p":"72f28a43-6552-49df-9cd6-8065539f8ce3","p2p_id":"CLSAIPECLL","cyclosing":null,"transshipment_count":0,"transit_time":5},{"id":"813482fe-0614-11ee-9560-00505683d611","carrier":{"id":93,"short_name":"Aliança","official_name":"Aliança Navegação e Logística","scac":"ALIU"},"pol":{"id":14470,"name":"San Antonio","locode":"CLSAI","longitude":-71.616667,"latitude":-33.583333},"pod":{"id":14950,"name":"Puerto Del Callao","locode":"PECLL","longitude":-77.15,"latitude":-12.05},"etd":"2023-07-02T03:00+0000","eta":"2023-07-07T17:00+0000","etd_local":"2023-07-01T23:00-0400","eta_local":"2023-07-07T12:00-0500","legs":[{"pol":{"id":14470,"name":"San Antonio","locode":"CLSAI","longitude":-71.616667,"latitude":-33.583333},"pod":{"id":14950,"name":"Puerto Del Callao","locode":"PECLL","longitude":-77.15,"latitude":-12.05},"etd":"2023-07-02T03:00+0000","eta":"2023-07-07T17:00+0000","etd_local":"2023-07-01T23:00-0400","eta_local":"2023-07-07T12:00-0500","carrier_id":93,"service_id":2090,"service_name":"CONOSUR SERVICE","service_code":"ABAC","voyage_number":"324W","vessel":{"id":52910,"shipname":"SAN ANTONIO EXPRESS","imo":9612777},"quality":0}],"alliance":{"id":999,"name":"Others"},"uuid_p2p":"3a4fb897-3692-47a7-bdf6-f1784fea58eb","p2p_id":"CLSAIPECLL","cyclosing":null,"transshipment_count":0,"transit_time":5},{"id":"81f84e96-0614-11ee-9560-00505683d611","carrier":{"id":95,"short_name":"APL","official_name":"American President Lines","scac":"APLU"},"pol":{"id":14470,"name":"San Antonio","locode":"CLSAI","longitude":-71.616667,"latitude":-33.583333},"pod":{"id":14950,"name":"Puerto Del Callao","locode":"PECLL","longitude":-77.15,"latitude":-12.05},"etd":"2023-06-09T16:00+0000","eta":"2023-06-12T17:00+0000","etd_local":"2023-06-09T12:00-0400","eta_local":"2023-06-12T12:00-0500","legs":[{"pol":{"id":14470,"name":"San Antonio","locode":"CLSAI","longitude":-71.616667,"latitude":-33.583333},"pod":{"id":14950,"name":"Puerto Del Callao","locode":"PECLL","longitude":-77.15,"latitude":-12.05},"etd":"2023-06-09T16:00+0000","eta":"2023-06-12T17:00+0000","etd_local":"2023-06-09T12:00-0400","eta_local":"2023-06-12T12:00-0500","carrier_id":95,"service_id":17180,"service_name":"EUROSAL XL SERVICE","service_code":"WCC","voyage_number":"0WCEWN1MA","vessel":{"id":3807632,"shipname":"COSCO SHIPPING VOLGA","imo":9731925},"quality":0}],"alliance":{"id":999,"name":"Others"},"uuid_p2p":"846a7276-b843-45e5-ba99-a068cf3b29e1","p2p_id":"CLSAIPECLL","cyclosing":null,"transshipment_count":0,"transit_time":3},{"id":"81f8558a-0614-11ee-9560-00505683d611","carrier":{"id":95,"short_name":"APL","official_name":"American President Lines","scac":"APLU"},"pol":{"id":14470,"name":"San Antonio","locode":"CLSAI","longitude":-71.616667,"latitude":-33.583333},"pod":{"id":14950,"name":"Puerto Del Callao","locode":"PECLL","longitude":-77.15,"latitude":-12.05},"etd":"2023-06-16T16:00+0000","eta":"2023-06-19T17:00+0000","etd_local":"2023-06-16T12:00-0400","eta_local":"2023-06-19T12:00-0500","legs":[{"pol":{"id":14470,"name":"San Antonio","locode":"CLSAI","longitude":-71.616667,"latitude":-33.583333},"pod":{"id":14950,"name":"Puerto Del Callao","locode":"PECLL","longitude":-77.15,"latitude":-12.05},"etd":"2023-06-16T16:00+0000","eta":"2023-06-19T17:00+0000","etd_local":"2023-06-16T12:00-0400","eta_local":"2023-06-19T12:00-0500","carrier_id":95,"service_id":17180,"service_name":"EUROSAL XL SERVICE","service_code":"WCC","voyage_number":"0WCT5N1MA","vessel":{"id":5764340,"shipname":"CMA CGM ESTELLE","imo":9729116},"quality":0}],"alliance":{"id":999,"name":"Others"},"uuid_p2p":"65e78179-eeaf-40c8-beb5-bcb371ed705a","p2p_id":"CLSAIPECLL","cyclosing":null,"transshipment_count":0,"transit_time":3},{"id":"81f8725e-0614-11ee-9560-00505683d611","carrier":{"id":95,"short_name":"APL","official_name":"American President Lines","scac":"APLU"},"pol":{"id":14470,"name":"San Antonio","locode":"CLSAI","longitude":-71.616667,"latitude":-33.583333},"pod":{"id":14950,"name":"Puerto Del Callao","locode":"PECLL","longitude":-77.15,"latitude":-12.05},"etd":"2023-06-23T16:00+0000","eta":"2023-06-26T17:00+0000","etd_local":"2023-06-23T12:00-0400","eta_local":"2023-06-26T12:00-0500","legs":[{"pol":{"id":14470,"name":"San Antonio","locode":"CLSAI","longitude":-71.616667,"latitude":-33.583333},"pod":{"id":14950,"name":"Puerto Del Callao","locode":"PECLL","longitude":-77.15,"latitude":-12.05},"etd":"2023-06-23T16:00+0000","eta":"2023-06-26T17:00+0000","etd_local":"2023-06-23T12:00-0400","eta_local":"2023-06-26T12:00-0500","carrier_id":95,"service_id":17180,"service_name":"EUROSAL XL SERVICE","service_code":"WCC","voyage_number":"0WCF0N1MA","vessel":{"id":3520932,"shipname":"VALPARAISO EXPRESS","imo":9777589},"quality":0}],"alliance":{"id":999,"name":"Others"},"uuid_p2p":"015dde6f-373b-4b17-9c42-19c77112f311","p2p_id":"CLSAIPECLL","cyclosing":null,"transshipment_count":0,"transit_time":3},{"id":"81f88c4e-0614-11ee-9560-00505683d611","carrier":{"id":95,"short_name":"APL","official_name":"American President Lines","scac":"APLU"},"pol":{"id":14470,"name":"San Antonio","locode":"CLSAI","longitude":-71.616667,"latitude":-33.583333},"pod":{"id":14950,"name":"Puerto Del Callao","locode":"PECLL","longitude":-77.15,"latitude":-12.05},"etd":"2023-06-30T16:00+0000","eta":"2023-07-03T17:00+0000","etd_local":"2023-06-30T12:00-0400","eta_local":"2023-07-03T12:00-0500","legs":[{"pol":{"id":14470,"name":"San Antonio","locode":"CLSAI","longitude":-71.616667,"latitude":-33.583333},"pod":{"id":14950,"name":"Puerto Del Callao","locode":"PECLL","longitude":-77.15,"latitude":-12.05},"etd":"2023-06-30T16:00+0000","eta":"2023-07-03T17:00+0000","etd_local":"2023-06-30T12:00-0400","eta_local":"2023-07-03T12:00-0500","carrier_id":95,"service_id":17180,"service_name":"EUROSAL XL SERVICE","service_code":"WCC","voyage_number":"0WCF2N1MA","vessel":{"id":28138689,"shipname":"BUENOS AIRES EXPRESS","imo":9932476},"quality":0}],"alliance":{"id":999,"name":"Others"},"uuid_p2p":"bcbb1f99-0308-478c-99de-d6fe0b100137","p2p_id":"CLSAIPECLL","cyclosing":null,"transshipment_count":0,"transit_time":3},{"id":"821bdba4-0614-11ee-9560-00505683d611","carrier":{"id":101,"short_name":"COSCO","official_name":"COSCO Shipping Lines","scac":"COSU"},"pol":{"id":14470,"name":"San Antonio","locode":"CLSAI","longitude":-71.616667,"latitude":-33.583333},"pod":{"id":14950,"name":"Puerto Del Callao","locode":"PECLL","longitude":-77.15,"latitude":-12.05},"etd":"2023-06-09T22:00+0000","eta":"2023-06-13T04:00+0000","etd_local":"2023-06-09T18:00-0400","eta_local":"2023-06-12T23:00-0500","legs":[{"pol":{"id":14470,"name":"San Antonio","locode":"CLSAI","longitude":-71.616667,"latitude":-33.583333},"pod":{"id":14950,"name":"Puerto Del Callao","locode":"PECLL","longitude":-77.15,"latitude":-12.05},"etd":"2023-06-09T22:00+0000","eta":"2023-06-13T04:00+0000","etd_local":"2023-06-09T18:00-0400","eta_local":"2023-06-12T23:00-0500","carrier_id":101,"service_id":13421,"service_name":"EUROPE SOUTH AMERICA WEST COAST SERVICE","service_code":"EWX","voyage_number":"3218N","vessel":{"id":3807632,"shipname":"COSCO SHIPPING VOLGA","imo":9731925},"quality":0}],"alliance":{"id":999,"name":"Others"},"uuid_p2p":"7efb337b-7bdb-495a-8469-3fbb01113608","p2p_id":"CLSAIPECLL","cyclosing":null,"transshipment_count":0,"transit_time":4},{"id":"821bfec2-0614-11ee-9560-00505683d611","carrier":{"id":101,"short_name":"COSCO","official_name":"COSCO Shipping Lines","scac":"COSU"},"pol":{"id":14470,"name":"San Antonio","locode":"CLSAI","longitude":-71.616667,"latitude":-33.583333},"pod":{"id":14950,"name":"Puerto Del Callao","locode":"PECLL","longitude":-77.15,"latitude":-12.05},"etd":"2023-06-17T03:00+0000","eta":"2023-06-20T04:00+0000","etd_local":"2023-06-16T23:00-0400","eta_local":"2023-06-19T23:00-0500","legs":[{"pol":{"id":14470,"name":"San Antonio","locode":"CLSAI","longitude":-71.616667,"latitude":-33.583333},"pod":{"id":14950,"name":"Puerto Del Callao","locode":"PECLL","longitude":-77.15,"latitude":-12.05},"etd":"2023-06-17T03:00+0000","eta":"2023-06-20T04:00+0000","etd_local":"2023-06-16T23:00-0400","eta_local":"2023-06-19T23:00-0500","carrier_id":101,"service_id":13421,"service_name":"EUROPE SOUTH AMERICA WEST COAST SERVICE","service_code":"EWX","voyage_number":"0WCT5N1MA","vessel":{"id":5764340,"shipname":"CMA CGM ESTELLE","imo":9729116},"quality":0}],"alliance":{"id":999,"name":"Others"},"uuid_p2p":"a842f5d6-6b85-4e61-a244-f8cd31fa4d7e","p2p_id":"CLSAIPECLL","cyclosing":null,"transshipment_count":0,"transit_time":3},{"id":"821c3784-0614-11ee-9560-00505683d611","carrier":{"id":101,"short_name":"COSCO","official_name":"COSCO Shipping Lines","scac":"COSU"},"pol":{"id":14470,"name":"San Antonio","locode":"CLSAI","longitude":-71.616667,"latitude":-33.583333},"pod":{"id":14950,"name":"Puerto Del Callao","locode":"PECLL","longitude":-77.15,"latitude":-12.05},"etd":"2023-06-24T03:00+0000","eta":"2023-06-27T04:00+0000","etd_local":"2023-06-23T23:00-0400","eta_local":"2023-06-26T23:00-0500","legs":[{"pol":{"id":14470,"name":"San Antonio","locode":"CLSAI","longitude":-71.616667,"latitude":-33.583333},"pod":{"id":14950,"name":"Puerto Del Callao","locode":"PECLL","longitude":-77.15,"latitude":-12.05},"etd":"2023-06-24T03:00+0000","eta":"2023-06-27T04:00+0000","etd_local":"2023-06-23T23:00-0400","eta_local":"2023-06-26T23:00-0500","carrier_id":101,"service_id":13421,"service_name":"EUROPE SOUTH AMERICA WEST COAST SERVICE","service_code":"EWX","voyage_number":"3220N","vessel":{"id":3520932,"shipname":"VALPARAISO EXPRESS","imo":9777589},"quality":0}],"alliance":{"id":999,"name":"Others"},"uuid_p2p":"71db0b98-b579-4707-8855-c6229253d523","p2p_id":"CLSAIPECLL","cyclosing":null,"transshipment_count":0,"transit_time":3},{"id":"821c5f34-0614-11ee-9560-00505683d611","carrier":{"id":101,"short_name":"COSCO","official_name":"COSCO Shipping Lines","scac":"COSU"},"pol":{"id":14470,"name":"San Antonio","locode":"CLSAI","longitude":-71.616667,"latitude":-33.583333},"pod":{"id":14950,"name":"Puerto Del Callao","locode":"PECLL","longitude":-77.15,"latitude":-12.05},"etd":"2023-07-01T03:00+0000","eta":"2023-07-04T04:00+0000","etd_local":"2023-06-30T23:00-0400","eta_local":"2023-07-03T23:00-0500","legs":[{"pol":{"id":14470,"name":"San Antonio","locode":"CLSAI","longitude":-71.616667,"latitude":-33.583333},"pod":{"id":14950,"name":"Puerto Del Callao","locode":"PECLL","longitude":-77.15,"latitude":-12.05},"etd":"2023-07-01T03:00+0000","eta":"2023-07-04T04:00+0000","etd_local":"2023-06-30T23:00-0400","eta_local":"2023-07-03T23:00-0500","carrier_id":101,"service_id":13421,"service_name":"EUROPE SOUTH AMERICA WEST COAST SERVICE","service_code":"EWX","voyage_number":"3221N","vessel":{"id":28138689,"shipname":"BUENOS AIRES EXPRESS","imo":9932476},"quality":0}],"alliance":{"id":999,"name":"Others"},"uuid_p2p":"a4186552-4a46-4191-8bfa-2e56656c769f","p2p_id":"CLSAIPECLL","cyclosing":null,"transshipment_count":0,"transit_time":3},{"id":"82e5c7f2-0614-11ee-9560-00505683d611","carrier":{"id":100,"short_name":"CMA CGM","official_name":"CMA CGM","scac":"CMDU"},"pol":{"id":14470,"name":"San Antonio","locode":"CLSAI","longitude":-71.616667,"latitude":-33.583333},"pod":{"id":14950,"name":"Puerto Del Callao","locode":"PECLL","longitude":-77.15,"latitude":-12.05},"etd":"2023-06-09T16:00+0000","eta":"2023-06-12T17:00+0000","etd_local":"2023-06-09T12:00-0400","eta_local":"2023-06-12T12:00-0500","legs":[{"pol":{"id":14470,"name":"San Antonio","locode":"CLSAI","longitude":-71.616667,"latitude":-33.583333},"pod":{"id":14950,"name":"Puerto Del Callao","locode":"PECLL","longitude":-77.15,"latitude":-12.05},"etd":"2023-06-09T16:00+0000","eta":"2023-06-12T17:00+0000","etd_local":"2023-06-09T12:00-0400","eta_local":"2023-06-12T12:00-0500","carrier_id":100,"service_id":6246,"service_name":"EUROSAL XL SERVICE","service_code":"WCC","voyage_number":"0WCEWN1MA","vessel":{"id":3807632,"shipname":"COSCO SHIPPING VOLGA","imo":9731925},"quality":0}],"alliance":{"id":999,"name":"Others"},"uuid_p2p":"a07e3d72-4d1e-471b-a80b-713b25c03447","p2p_id":"CLSAIPECLL","cyclosing":"2023-06-05T16:00+0000","transshipment_count":0,"transit_time":3},{"id":"82e5d774-0614-11ee-9560-00505683d611","carrier":{"id":100,"short_name":"CMA CGM","official_name":"CMA CGM","scac":"CMDU"},"pol":{"id":14470,"name":"San Antonio","locode":"CLSAI","longitude":-71.616667,"latitude":-33.583333},"pod":{"id":14950,"name":"Puerto Del Callao","locode":"PECLL","longitude":-77.15,"latitude":-12.05},"etd":"2023-06-16T16:00+0000","eta":"2023-06-19T17:00+0000","etd_local":"2023-06-16T12:00-0400","eta_local":"2023-06-19T12:00-0500","legs":[{"pol":{"id":14470,"name":"San Antonio","locode":"CLSAI","longitude":-71.616667,"latitude":-33.583333},"pod":{"id":14950,"name":"Puerto Del Callao","locode":"PECLL","longitude":-77.15,"latitude":-12.05},"etd":"2023-06-16T16:00+0000","eta":"2023-06-19T17:00+0000","etd_local":"2023-06-16T12:00-0400","eta_local":"2023-06-19T12:00-0500","carrier_id":100,"service_id":6246,"service_name":"EUROSAL XL SERVICE","service_code":"WCC","voyage_number":"0WCT5N1MA","vessel":{"id":5764340,"shipname":"CMA CGM ESTELLE","imo":9729116},"quality":0}],"alliance":{"id":999,"name":"Others"},"uuid_p2p":"97a9137c-44bf-4eef-870d-15549de6ed25","p2p_id":"CLSAIPECLL","cyclosing":"2023-06-12T16:00+0000","transshipment_count":0,"transit_time":3},{"id":"82e5fa06-0614-11ee-9560-00505683d611","carrier":{"id":100,"short_name":"CMA CGM","official_name":"CMA CGM","scac":"CMDU"},"pol":{"id":14470,"name":"San Antonio","locode":"CLSAI","longitude":-71.616667,"latitude":-33.583333},"pod":{"id":14950,"name":"Puerto Del Callao","locode":"PECLL","longitude":-77.15,"latitude":-12.05},"etd":"2023-06-23T16:00+0000","eta":"2023-06-26T17:00+0000","etd_local":"2023-06-23T12:00-0400","eta_local":"2023-06-26T12:00-0500","legs":[{"pol":{"id":14470,"name":"San Antonio","locode":"CLSAI","longitude":-71.616667,"latitude":-33.583333},"pod":{"id":14950,"name":"Puerto Del Callao","locode":"PECLL","longitude":-77.15,"latitude":-12.05},"etd":"2023-06-23T16:00+0000","eta":"2023-06-26T17:00+0000","etd_local":"2023-06-23T12:00-0400","eta_local":"2023-06-26T12:00-0500","carrier_id":100,"service_id":6246,"service_name":"EUROSAL XL SERVICE","service_code":"WCC","voyage_number":"0WCF0N1MA","vessel":{"id":3520932,"shipname":"VALPARAISO EXPRESS","imo":9777589},"quality":0}],"alliance":{"id":999,"name":"Others"},"uuid_p2p":"53dfd85e-38bc-4f09-b622-ae73d8a9b75a","p2p_id":"CLSAIPECLL","cyclosing":"2023-06-19T16:00+0000","transshipment_count":0,"transit_time":3},{"id":"82e61b1c-0614-11ee-9560-00505683d611","carrier":{"id":100,"short_name":"CMA CGM","official_name":"CMA CGM","scac":"CMDU"},"pol":{"id":14470,"name":"San Antonio","locode":"CLSAI","longitude":-71.616667,"latitude":-33.583333},"pod":{"id":14950,"name":"Puerto Del Callao","locode":"PECLL","longitude":-77.15,"latitude":-12.05},"etd":"2023-06-30T16:00+0000","eta":"2023-07-03T17:00+0000","etd_local":"2023-06-30T12:00-0400","eta_local":"2023-07-03T12:00-0500","legs":[{"pol":{"id":14470,"name":"San Antonio","locode":"CLSAI","longitude":-71.616667,"latitude":-33.583333},"pod":{"id":14950,"name":"Puerto Del Callao","locode":"PECLL","longitude":-77.15,"latitude":-12.05},"etd":"2023-06-30T16:00+0000","eta":"2023-07-03T17:00+0000","etd_local":"2023-06-30T12:00-0400","eta_local":"2023-07-03T12:00-0500","carrier_id":100,"service_id":6246,"service_name":"EUROSAL XL SERVICE","service_code":"WCC","voyage_number":"0WCF2N1MA","vessel":{"id":28138689,"shipname":"BUENOS AIRES EXPRESS","imo":9932476},"quality":0}],"alliance":{"id":999,"name":"Others"},"uuid_p2p":"c4c2ecc6-a590-4cae-acf4-adac5f993bb1","p2p_id":"CLSAIPECLL","cyclosing":"2023-06-26T16:00+0000","transshipment_count":0,"transit_time":3},{"id":"83734bea-0614-11ee-9560-00505683d611","carrier":{"id":114,"short_name":"Hamburg Süd","official_name":"Hamburg Süd","scac":"SUDU"},"pol":{"id":14470,"name":"San Antonio","locode":"CLSAI","longitude":-71.616667,"latitude":-33.583333},"pod":{"id":14950,"name":"Puerto Del Callao","locode":"PECLL","longitude":-77.15,"latitude":-12.05},"etd":"2023-06-11T03:00+0000","eta":"2023-06-16T17:00+0000","etd_local":"2023-06-10T23:00-0400","eta_local":"2023-06-16T12:00-0500","legs":[{"pol":{"id":14470,"name":"San Antonio","locode":"CLSAI","longitude":-71.616667,"latitude":-33.583333},"pod":{"id":14950,"name":"Puerto Del Callao","locode":"PECLL","longitude":-77.15,"latitude":-12.05},"etd":"2023-06-11T03:00+0000","eta":"2023-06-16T17:00+0000","etd_local":"2023-06-10T23:00-0400","eta_local":"2023-06-16T12:00-0500","carrier_id":114,"service_id":1194,"service_name":"CONOSUR SERVICE","service_code":"ABAC","voyage_number":"321W","vessel":{"id":11001,"shipname":"ANTOFAGASTA EXPRESS","imo":9612789},"quality":0}],"alliance":{"id":999,"name":"Others"},"uuid_p2p":"f907bc24-4b73-416e-adca-cc86ef289ea3","p2p_id":"CLSAIPECLL","cyclosing":null,"transshipment_count":0,"transit_time":5},{"id":"84b7a7d0-0614-11ee-9560-00505683d611","carrier":{"id":155,"short_name":"Sealand Americas","official_name":"Sealand Americas","scac":"SEAU"},"pol":{"id":14470,"name":"San Antonio","locode":"CLSAI","longitude":-71.616667,"latitude":-33.583333},"pod":{"id":14950,"name":"Puerto Del Callao","locode":"PECLL","longitude":-77.15,"latitude":-12.05},"etd":"2023-06-11T17:00+0000","eta":"2023-06-16T15:00+0000","etd_local":"2023-06-11T13:00-0400","eta_local":"2023-06-16T10:00-0500","legs":[{"pol":{"id":14470,"name":"San Antonio","locode":"CLSAI","longitude":-71.616667,"latitude":-33.583333},"pod":{"id":14950,"name":"Puerto Del Callao","locode":"PECLL","longitude":-77.15,"latitude":-12.05},"etd":"2023-06-11T17:00+0000","eta":"2023-06-16T15:00+0000","etd_local":"2023-06-11T13:00-0400","eta_local":"2023-06-16T10:00-0500","carrier_id":155,"service_id":13943,"service_name":"CONOSUR SERVICE","service_code":"ABAC","voyage_number":"321W","vessel":{"id":11001,"shipname":"ANTOFAGASTA EXPRESS","imo":9612789},"quality":0}],"alliance":{"id":999,"name":"Others"},"uuid_p2p":"12b7564e-ee7a-47fc-af5a-62d426130820","p2p_id":"CLSAIPECLL","cyclosing":"2023-06-09T03:00+0000","transshipment_count":0,"transit_time":5}],"completed":true,"etd":"2023-05-25","eta":null,"weeks":6,"allroutes":false,"carrier":null,"direct":false,"num_results":36}